HanhanAI/__init__.py
HanhanAI/ga_brain.py
HanhanAI/population.py
HanhanAI/universal_dqn.py
HanhanAI-2.0.2.dist-info/LICENSE
HanhanAI-2.0.2.dist-info/METADATA
HanhanAI-2.0.2.dist-info/WHEEL
HanhanAI-2.0.2.dist-info/top_level.txt
HanhanAI-2.0.2.dist-info/RECORD
