Metadata-Version: 2.1
Name: HanhanAI
Version: 2.0.2
Summary: Universal game AI system for game developer
Home-page: https://github.com/hanhan-ai/2019HanHan
Author: HanhanAI producer1
Author-email: 1379612504@qq.com
Maintainer: HanhanAI producer2
Maintainer-email: 762613908@qq.com
License: MIT
Platform: all
Classifier: Development Status :: 2 - Pre-Alpha
Classifier: Environment :: Console
Classifier: Intended Audience :: Developers
Classifier: Natural Language :: Chinese (Simplified)
Classifier: Operating System :: Microsoft :: Windows :: Windows 10
Classifier: Programming Language :: Python
Classifier: Programming Language :: Python :: 3.7
Classifier: Topic :: Adaptive Technologies
Requires-Dist: keras (>=2.2.5)
Requires-Dist: numpy (>=1.17.0)
Requires-Dist: matplotlib (>=3.1.1)
